AutoCarver/__init__.py
AutoCarver/carvers/__init__.py
AutoCarver/carvers/binary_carver.py
AutoCarver/carvers/continuous_carver.py
AutoCarver/carvers/multiclass_carver.py
AutoCarver/carvers/utils/__init__.py
AutoCarver/carvers/utils/base_carver.py
AutoCarver/carvers/utils/pretty_print.py
AutoCarver/combinations/__init__.py
AutoCarver/combinations/binary/__init__.py
AutoCarver/combinations/binary/binary_combination_evaluators.py
AutoCarver/combinations/binary/binary_target_rates.py
AutoCarver/combinations/continuous/__init__.py
AutoCarver/combinations/continuous/continuous_combination_evaluators.py
AutoCarver/combinations/continuous/continuous_target_rates.py
AutoCarver/combinations/utils/__init__.py
AutoCarver/combinations/utils/combination_evaluator.py
AutoCarver/combinations/utils/combinations.py
AutoCarver/combinations/utils/target_rate.py
AutoCarver/combinations/utils/testing.py
AutoCarver/config.py
AutoCarver/discretizers/__init__.py
AutoCarver/discretizers/discretizer.py
AutoCarver/discretizers/qualitatives/__init__.py
AutoCarver/discretizers/qualitatives/categorical_discretizer.py
AutoCarver/discretizers/qualitatives/chained_discretizer.py
AutoCarver/discretizers/qualitatives/ordinal_discretizer.py
AutoCarver/discretizers/qualitatives/qualitative_discretizer.py
AutoCarver/discretizers/quantitatives/__init__.py
AutoCarver/discretizers/quantitatives/continuous_discretizer.py
AutoCarver/discretizers/quantitatives/quantitative_discretizer.py
AutoCarver/discretizers/utils/__init__.py
AutoCarver/discretizers/utils/base_discretizer.py
AutoCarver/discretizers/utils/multiprocessing.py
AutoCarver/discretizers/utils/type_discretizers.py
AutoCarver/features/__init__.py
AutoCarver/features/features.py
AutoCarver/features/qualitatives/__init__.py
AutoCarver/features/qualitatives/categorical_feature.py
AutoCarver/features/qualitatives/ordinal_feature.py
AutoCarver/features/qualitatives/qualitative_feature.py
AutoCarver/features/quantitatives/__init__.py
autocarver-7.0.10.dist-info/LICENSE
autocarver-7.0.10.dist-info/METADATA
autocarver-7.0.10.dist-info/WHEEL
autocarver-7.0.10.dist-info/RECORD
