Metadata-Version: 2.3
Name: AutoCarver
Version: 7.0.10
Summary: Automatic Discretization of Features with Optimal Target Association
License: MIT
Author: Mario DEFRANCE
Author-email: defrancemario@gmail.com
Requires-Python: >=3.9,<3.13
Classifier: Development Status :: 5 - Production/Stable
Classifier: License :: OSI Approved :: MIT License
Classifier: Operating System :: MacOS :: MacOS X
Classifier: Operating System :: Microsoft :: Windows
Classifier: Operating System :: Unix
Classifier: Programming Language :: Python :: 3
Classifier: Programming Language :: Python :: 3.9
Classifier: Programming Language :: Python :: 3.10
Classifier: Programming Language :: Python :: 3.11
Classifier: Programming Language :: Python :: 3.12
Provides-Extra: dev
Provides-Extra: docs
Provides-Extra: jupyter
Provides-Extra: tests
Requires-Dist: Flake8-pyproject (>=1.2.3,<2.0.0) ; extra == "tests"
Requires-Dist: black (>=23.12.0,<24.0.0) ; extra == "tests"
Requires-Dist: flake8 (>=6.1.0,<7.0.0) ; extra == "tests"
Requires-Dist: icecream (>=2.1.3,<3.0.0) ; extra == "tests"
Requires-Dist: ipykernel (>=6.27.1,<7.0.0) ; extra == "jupyter" or extra == "dev"
Requires-Dist: ipython (>=8.18.1,<9.0.0) ; extra == "jupyter"
Requires-Dist: ipywidgets (>=8.1.5,<9.0.0) ; extra == "dev"
Requires-Dist: isort (>=5.13.2,<6.0.0) ; extra == "tests"
Requires-Dist: jinja2 (>=3.1.5,<4.0.0) ; extra == "jupyter"
Requires-Dist: matplotlib (>=3.8.2,<4.0.0) ; extra == "jupyter"
Requires-Dist: nbsphinx (==0.9.6) ; extra == "docs"
Requires-Dist: numpy (>=1.24.2,<2.1)
Requires-Dist: pandas (>=2.1.4,<3.0.0)
Requires-Dist: pylint (>=3.0.3,<4.0.0) ; extra == "tests"
Requires-Dist: pypandoc (>=1.12,<2.0) ; extra == "docs"
Requires-Dist: pytest (>=7.4.3,<8.0.0) ; extra == "tests"
Requires-Dist: pytest-cov (>=4.1.0,<5.0.0) ; extra == "tests"
Requires-Dist: scikit-learn (>=1.3.2,<2.0.0)
Requires-Dist: scipy (>=1.11.4,<2.0.0)
Requires-Dist: sphinx (==7.4.7) ; extra == "docs"
Requires-Dist: sphinx-rtd-theme (==2.0.0) ; extra == "docs"
Requires-Dist: statsmodels (>=0.13)
Requires-Dist: toml (>=0.10.2,<0.11.0) ; extra == "docs"
Requires-Dist: tqdm (>=4.66.1,<5.0.0)
Requires-Dist: xgboost (>=2.1.3,<3.0.0) ; extra == "dev"
Project-URL: docs, https://autocarver.readthedocs.io/en/latest/index.html
Project-URL: repository, https://github.com/mdefrance/AutoCarver
